lmd/__init__.py
lmd/cli.py
lmd/lmd.py
lmd/utils.py
nlp.lmd-0.2.0.dist-info/LICENSE
nlp.lmd-0.2.0.dist-info/METADATA
nlp.lmd-0.2.0.dist-info/WHEEL
nlp.lmd-0.2.0.dist-info/entry_points.txt
nlp.lmd-0.2.0.dist-info/top_level.txt
nlp.lmd-0.2.0.dist-info/RECORD
