Metadata-Version: 2.1
Name: nlp.lmd
Version: 0.2.0
Summary: Language Model Decomposition
Home-page: https://github.com/haozhg/lmd
Author: Hao Zhang
Author-email: haozhang@alumni.princeton.edu
License: Apache Software License 2.0
Keywords: nlp,machine learning,natural language processing,deep learning,language models,transformers,pre-trained models
Classifier: Development Status :: 2 - Pre-Alpha
Classifier: Intended Audience :: Developers
Classifier: License :: OSI Approved :: Apache Software License
Classifier: Natural Language :: English
Classifier: Programming Language :: Python :: 3
Classifier: Programming Language :: Python :: 3.8
Classifier: Programming Language :: Python :: 3.9
Classifier: Programming Language :: Python :: 3.10
Requires-Python: >=3.8
License-File: LICENSE
Requires-Dist: transformers
Requires-Dist: datasets
Requires-Dist: torch
Requires-Dist: tqdm
Requires-Dist: pandas
